MANIFEST.in
README.md
requirements.txt
setup.py
ipyats/__init__.py
ipyats/main.py
ipyats.egg-info/PKG-INFO
ipyats.egg-info/SOURCES.txt
ipyats.egg-info/dependency_links.txt
ipyats.egg-info/entry_points.txt
ipyats.egg-info/requires.txt
ipyats.egg-info/top_level.txt
ipyats/public_testbeds/devnet_sandbox.yaml
ipyats/tasks/__init__.py
ipyats/utils/__init__.py