Metadata-Version: 2.1
Name: ipyats
Version: 0.2.0
Summary: Interactive pyATS
Home-page: https://github.com/CiscoDevNet/ipyats
Author: Kevin Corbin
Author-email: kecorbin@cisco.com
License: UNKNOWN
Project-URL: Bug Reports, https://github.com/CiscoDevNet/ipyats/issues
Project-URL: Source, https://github.com/CiscoDevNet/ipyats/
Keywords: pyats genie development cisco network automation
Platform: UNKNOWN
Classifier: Development Status :: 3 - Alpha
Classifier: Intended Audience :: Developers
Classifier: Topic :: Software Development :: Build Tools
Classifier: License :: OSI Approved :: MIT License
Classifier: Programming Language :: Python :: 3.4
Classifier: Programming Language :: Python :: 3.5
Classifier: Programming Language :: Python :: 3.6
Provides-Extra: test
Provides-Extra: dev
